git_branchless-0.0.6.data/scripts/git-branchless-pick
gitbranchless/__init__.py
gitbranchless/main.py
git_branchless-0.0.6.dist-info/LICENSE
git_branchless-0.0.6.dist-info/METADATA
git_branchless-0.0.6.dist-info/WHEEL
git_branchless-0.0.6.dist-info/entry_points.txt
git_branchless-0.0.6.dist-info/top_level.txt
git_branchless-0.0.6.dist-info/RECORD
