Metadata-Version: 2.1
Name: git-branchless
Version: 0.0.6
Summary: Efficiently manage Git branches without leaving your local branch
Home-page: https://git.sr.ht/~krobelus/git-branchless/
Author: Johannes Altmanninger
Author-email: aclopte@gmail.com
License: MIT
Project-URL: Bug Tracker, https://github.com/krobelus/git-branchless/issues/
Project-URL: Source Code, https://git.sr.ht/~krobelus/git-branchless/
Project-URL: Documentation, https://git.sr.ht/~krobelus/git-branchless/
Keywords: git branch-workflow pull-request patch-stack
Platform: UNKNOWN
Classifier: Development Status :: 4 - Beta
Classifier: Intended Audience :: Developers
Classifier: Environment :: Console
Classifier: Topic :: Software Development :: Version Control
Classifier: Topic :: Software Development :: Version Control :: Git
Classifier: License :: OSI Approved :: MIT License
Classifier: Programming Language :: Python :: 3
Classifier: Programming Language :: Python :: 3.6
Classifier: Programming Language :: Python :: 3.7
Classifier: Programming Language :: Python :: 3.8
Classifier: Programming Language :: Python :: 3.9
Requires-Python: >=3.6
License-File: LICENSE
